buildABot/Analytics.py
buildABot/BotHelper.py
buildABot/BotManager.py
buildABot/Entities.py
buildABot/FallbackSocialTag.py
buildABot/Firebase_Learn.py
buildABot/Firebase_Reco.py
buildABot/Intents.py
buildABot/LearnMenu.py
buildABot/Para.py
buildABot/Paraphraser.py
buildABot/Password.py
buildABot/QA.py
buildABot/QAHelper.py
buildABot/QAManager.py
buildABot/RecommendedMenu.py
buildABot/Responses.py
buildABot/TelegramLogs.py
buildABot/WebApp_Learn.py
buildABot/WebApp_Reco.py
buildABot/Webhook_Learn.py
buildABot/Webhook_Reco.py
buildABot/Worksheets_Learn.py
buildABot/Worksheets_Reco.py
buildABot/__init__.py
buildABot/Data/__init__.py
buildABot/Data/Default - Learn/Default Fallback Intent.json
buildABot/Data/Default - Learn/Default Welcome Intent - fallback.json
buildABot/Data/Default - Learn/Default Welcome Intent.json
buildABot/Data/Default - Learn/Default Welcome Intent_usersays_en.json
buildABot/Data/Default - Learn/Downvote.json
buildABot/Data/Default - Learn/Downvote_usersays_en.json
buildABot/Data/Default - Learn/Email Enquiry.json
buildABot/Data/Default - Learn/Email Enquiry_usersays_en.json
buildABot/Data/Default - Learn/Exit Conversation.json
buildABot/Data/Default - Learn/Exit Conversation_usersays_en.json
buildABot/Data/Default - Learn/Fallback - Logged In - fallback.json
buildABot/Data/Default - Learn/Fallback - Logged In - no.json
buildABot/Data/Default - Learn/Fallback - Logged In - no_usersays_en.json
buildABot/Data/Default - Learn/Fallback - Logged In - yes.json
buildABot/Data/Default - Learn/Fallback - Logged In - yes_usersays_en.json
buildABot/Data/Default - Learn/Log In - Remember Name.json
buildABot/Data/Default - Learn/Log In - Remember Name_usersays_en.json
buildABot/Data/Default - Learn/Log In - Results - Password - Correct.json
buildABot/Data/Default - Learn/Log In - Results - Password - Correct_usersays_en.json
buildABot/Data/Default - Learn/Log In - Results - Password - fallback - fallback - fallback.json
TPE_Bot-3.1.0.dist-info/METADATA
TPE_Bot-3.1.0.dist-info/WHEEL
TPE_Bot-3.1.0.dist-info/top_level.txt
TPE_Bot-3.1.0.dist-info/RECORD
