Metadata-Version: 2.1
Name: TPE-Bot
Version: 3.1.0
Summary: A TPEdu All-in-one Chatbot Package
Author: Ester Goh
Classifier: Programming Language :: Python :: 3
Classifier: Operating System :: OS Independent
Requires-Python: >=3.9
Requires-Dist: pandas
Requires-Dist: torch
Requires-Dist: openpyxl
Requires-Dist: transformers
Requires-Dist: sentencepiece
Requires-Dist: python-Levenshtein
Requires-Dist: sentence-transformers
Requires-Dist: fuzzywuzzy
Requires-Dist: protobuf (==3.20.0)
